{
  "Name": "Biblical Studies",
  "Code": "BIBLSTUD",
  "Courses": [
    {
      "Name": "BIBLSTUD 5110A - INTRO TO BIBLE AS SCRIPTURE",
      "Description": [],
      "Components": [
        {
          "Section": "550",
          "Component": "LEC",
          "Class Nbr": "1956",
          "Days": [
            "Tu"
          ],
          "Start Time": "6:00 PM",
          "End Time": "8:30 PM",
          "Location": "HC-W4",
          "Instructor": "D. Smith",
          "Notes": [
            "RESTRICTED TO THEOLOGY MASTERS STUDENTS AT HURON."
          ],
          "Status": "Not Full",
          "Campus": "Huron",
          "Delivery": "In Person"
        }
      ]
    },
    {
      "Name": "BIBLSTUD 5116B - THE NEW TESTAMENT WRITINGS",
      "Description": [],
      "Components": [
        {
          "Section": "550",
          "Component": "LEC",
          "Class Nbr": "1955",
          "Days": [
            "Tu"
          ],
          "Start Time": "6:00 PM",
          "End Time": "8:30 PM",
          "Location": "HC-W4",
          "Instructor": "J. QuigleyJennifer",
          "Notes": [
            "RESTRICTED TO THEOLOGY MASTERS STUDENTS AT HURON. ",
            "REQUISITES: Prerequisite: the former Biblical Studies 5103A/B or Biblical Studies 5110A/B"
          ],
          "Status": "Not Full",
          "Campus": "Huron",
          "Delivery": "In Person"
        }
      ]
    },
    {
      "Name": "BIBLSTUD 5120B - INTRO TO THE HEBREW BIBLE",
      "Description": [],
      "Components": [
        {
          "Section": "550",
          "Component": "LEC",
          "Class Nbr": "2012",
          "Days": [
            "Th"
          ],
          "Start Time": "11:30 AM",
          "End Time": "2:00 PM",
          "Location": "HC-W104",
          "Instructor": "N. Meyer",
          "Notes": [
            "RESTRICTED TO THEOLOGY MASTERS STUDENTS AT HURON."
          ],
          "Status": "Not Full",
          "Campus": "Huron",
          "Delivery": "In Person"
        }
      ]
    },
    {
      "Name": "BIBLSTUD 5222A - PROPHETIC LITERATURE",
      "Description": [],
      "Components": [
        {
          "Section": "550",
          "Component": "LEC",
          "Class Nbr": "2356",
          "Days": [
            "Th"
          ],
          "Start Time": "11:30 AM",
          "End Time": "2:00 PM",
          "Location": "HC-W104",
          "Instructor": "T. Lemos",
          "Notes": [
            "CROSS-LISTED WITH RELSTUD 4040A. ",
            "REQUISITES: Prerequisite: the former Biblical Studies 5104B; or Biblical Studies 5112A/B and 5114A/B"
          ],
          "Status": "Not Full",
          "Campus": "Huron",
          "Delivery": "In Person"
        }
      ]
    },
    {
      "Name": "BIBLSTUD 5255A - SPECIAL TOPICS COURSE",
      "Description": [
        "Topic is available in the office of the Dean of Theology.",
        "Extra Information: 3 hours."
      ],
      "Components": [
        {
          "Section": "550",
          "Component": "LEC",
          "Class Nbr": "12583",
          "Days": [
            "Th"
          ],
          "Start Time": "8:30 AM",
          "End Time": "11:00 AM",
          "Location": "HC-V208",
          "Instructor": "J. QuigleyJennifer",
          "Notes": [],
          "Status": "Not Full",
          "Campus": "Huron",
          "Delivery": "In Person"
        }
      ]
    }
  ]
}