{
  "Name": "Pastoral Theology",
  "Code": "PASTTHEO",
  "Courses": [
    {
      "Name": "PASTTHEO 5213B - INTEGRATIVE SEMINAR",
      "Description": [],
      "Components": [
        {
          "Section": "550",
          "Component": "LEC",
          "Class Nbr": "1991",
          "Days": [
            "Th"
          ],
          "Start Time": "8:30 AM",
          "End Time": "11:00 AM",
          "Location": "HC-W4",
          "Instructor": "D. Marks",
          "Notes": [
            "RESTRICTED TO THEOLOGY MASTERS STUDENTS AT HURON."
          ],
          "Status": "Not Full",
          "Campus": "Huron",
          "Delivery": "In Person"
        }
      ]
    },
    {
      "Name": "PASTTHEO 5230A - CONGRGTNL DEVELPMNT & LEADRSHP",
      "Description": [],
      "Components": [
        {
          "Section": "550",
          "Component": "LEC",
          "Class Nbr": "2261",
          "Days": [
            "Tu"
          ],
          "Start Time": "2:30 PM",
          "End Time": "5:00 PM",
          "Location": "HC-W4",
          "Instructor": "B. Morrison",
          "Notes": [],
          "Status": "Not Full",
          "Campus": "Huron",
          "Delivery": "In Person"
        }
      ]
    },
    {
      "Name": "PASTTHEO 5231A - PASTORAL CARE & CONSELLING",
      "Description": [],
      "Components": [
        {
          "Section": "550",
          "Component": "LEC",
          "Class Nbr": "1987",
          "Days": [
            "Tu"
          ],
          "Start Time": "6:00 PM",
          "End Time": "8:30 PM",
          "Location": "HC-W104",
          "Instructor": "B. Morrison",
          "Notes": [
            "RESTRICTED TO THEOLOGY MASTERS STUDENTS AT HURON OR ST. PETER'S SEMINARY. ",
            "REQUISITES: Prerequisite: Field Educ 5110 A/B"
          ],
          "Status": "Not Full",
          "Campus": "Huron",
          "Delivery": "In Person"
        }
      ]
    },
    {
      "Name": "PASTTHEO 5305A - THEOLOGICAL REFLECTION",
      "Description": [],
      "Components": [
        {
          "Section": "550",
          "Component": "LEC",
          "Class Nbr": "2343",
          "Days": [
            "W"
          ],
          "Start Time": "2:30 PM",
          "End Time": "5:00 PM",
          "Location": "HC-H119",
          "Instructor": "T. Connor",
          "Notes": [],
          "Status": "Not Full",
          "Campus": "Huron",
          "Delivery": "In Person"
        }
      ]
    },
    {
      "Name": "PASTTHEO 5313B - MDIV INTEGRATION AND FORMATION",
      "Description": [
        "Through participation in formation events and opportunities, and through the integration of learning, MDiv students will have the opportunity to reinforce and master core goals of the program."
      ],
      "Components": [
        {
          "Section": "550",
          "Component": "LEC",
          "Class Nbr": "2034",
          "Days": [],
          "Start Time": "",
          "End Time": "",
          "Location": "",
          "Instructor": "D. Davis",
          "Notes": [],
          "Status": "Not Full",
          "Campus": "Huron",
          "Delivery": "In Person"
        }
      ]
    },
    {
      "Name": "PASTTHEO 5333B - GRIEF, CRISIS & PASTORAL CARE",
      "Description": [],
      "Components": [
        {
          "Section": "550",
          "Component": "LEC",
          "Class Nbr": "2344",
          "Days": [
            "Tu"
          ],
          "Start Time": "6:00 PM",
          "End Time": "8:30 PM",
          "Location": "HC-W104",
          "Instructor": "B. Morrison",
          "Notes": [
            "REQUISITES: Prerequisite(s): Pastoral Theology 5231A/B"
          ],
          "Status": "Not Full",
          "Campus": "Huron",
          "Delivery": "In Person"
        }
      ]
    },
    {
      "Name": "PASTTHEO 5576A - ETHICAL ISSUES & PASTORAL MIN",
      "Description": [],
      "Components": [
        {
          "Section": "570",
          "Component": "LEC",
          "Class Nbr": "1399",
          "Days": [],
          "Start Time": "",
          "End Time": "",
          "Location": "",
          "Instructor": "P. Keller",
          "Notes": [],
          "Status": "Not Full",
          "Campus": "King's",
          "Delivery": "In Person"
        }
      ]
    }
  ]
}